care_query/__init__.py
care_query/care_query.py
care_query/care_query_data.py
care_query/care_query_user.py
care_query/care_query_utils.py
care_query/field-values.json
care_query/field_value_data.py
care_query/glossary.py
care_query-1.1.11.dist-info/LICENSE
care_query-1.1.11.dist-info/METADATA
care_query-1.1.11.dist-info/WHEEL
care_query-1.1.11.dist-info/top_level.txt
care_query-1.1.11.dist-info/RECORD
