Metadata-Version: 2.1
Name: care_query
Version: 1.1.11
Summary: Monocle Insight's CareQuery API
Author-email: Sean O'Malley <somalley@monocleinsights.com>, Ray Deiotte <rdeiotte@monocleinsights.com>
Project-URL: Homepage, https://care-query.readme.io/
Classifier: Programming Language :: Python :: 3
Classifier: License :: OSI Approved :: MIT License
Classifier: Operating System :: OS Independent
Requires-Python: >=3.7
License-File: LICENSE
